setup.py
tx_easy_pika.egg-info/PKG-INFO
tx_easy_pika.egg-info/SOURCES.txt
tx_easy_pika.egg-info/dependency_links.txt
tx_easy_pika.egg-info/requires.txt
tx_easy_pika.egg-info/top_level.txt
txeasypika/__init__.py