Metadata-Version: 1.1
Name: tx-easy-pika
Version: 1.0.1
Summary: Wrapper around Pika's Twisted connection to make it simpler to work with.
Home-page: http://github.com/SweetIQ/tx-easy-pika
Author: SweetIQ
Author-email: rob@sweetiq.com
License: UNKNOWN
Keywords: pika,rabbitmq,twisted,amqpy
Platform: UNKNOWN
Classifier: Programming Language :: Python
Classifier: License :: OSI Approved :: MIT License
Classifier: Development Status :: 3 - Alpha
Classifier: Intended Audience :: Developers
